uncertainty_engine_types/__init__.py
uncertainty_engine_types/chat_history.py
uncertainty_engine_types/context.py
uncertainty_engine_types/dataset.py
uncertainty_engine_types/embeddings.py
uncertainty_engine_types/execution_error.py
uncertainty_engine_types/file.py
uncertainty_engine_types/graph.py
uncertainty_engine_types/handle.py
uncertainty_engine_types/id.py
uncertainty_engine_types/job.py
uncertainty_engine_types/llm.py
uncertainty_engine_types/message.py
uncertainty_engine_types/model.py
uncertainty_engine_types/model_config.py
uncertainty_engine_types/node_info.py
uncertainty_engine_types/prompt.py
uncertainty_engine_types/run_workflow.py
uncertainty_engine_types/sensor_designer.py
uncertainty_engine_types/sql.py
uncertainty_engine_types/token.py
uncertainty_engine_types/tool_metadata.py
uncertainty_engine_types/uncertainty_plot.py
uncertainty_engine_types/utils.py
uncertainty_engine_types/vector_store.py
uncertainty_engine_types/version.py
uncertainty_engine_types-0.16.0.dist-info/METADATA
uncertainty_engine_types-0.16.0.dist-info/WHEEL
uncertainty_engine_types-0.16.0.dist-info/RECORD
