Metadata-Version: 2.3
Name: uncertainty-engine-types
Version: 0.16.0
Summary: Common type definitions for the Uncertainty Engine
Author: Freddy Wordingham
Author-email: freddy@digilab.ai
Requires-Python: >=3.10,<4.0
Classifier: Programming Language :: Python :: 3
Classifier: Programming Language :: Python :: 3.10
Classifier: Programming Language :: Python :: 3.11
Classifier: Programming Language :: Python :: 3.12
Classifier: Programming Language :: Python :: 3.13
Requires-Dist: pydantic (>=2.10.5,<3.0.0)
